{
  "lang":"en",
  "name":"pipeline",
  "version":"0.0.0",
  "spacy_version":">=3.0.6,<3.1.0",
  "description":"",
  "author":"",
  "email":"",
  "url":"",
  "license":"",
  "spacy_git_version":"df3444421",
  "vectors":{
    "width":0,
    "vectors":0,
    "keys":0,
    "name":null
  },
  "labels":{
    "tok2vec":[

    ],
    "ner":[
      "MISC",
      "ORG",
      "PER"
    ]
  },
  "pipeline":[
    "tok2vec",
    "ner"
  ],
  "components":[
    "tok2vec",
    "ner"
  ],
  "disabled":[

  ],
  "performance":{
    "ents_per_type":{
      "PER":{
        "p":1.0,
        "r":1.0,
        "f":1.0
      },
      "ORG":{
        "p":0.9682539683,
        "r":0.9682539683,
        "f":0.9682539683
      },
      "MISC":{
        "p":0.96,
        "r":1.0,
        "f":0.9795918367
      }
    },
    "ents_f":0.9874686717,
    "ents_p":0.985,
    "ents_r":0.9899497487,
    "tok2vec_loss":150.2630179768,
    "ner_loss":225.9733636211
  }
}